reswarm/AutobahnConnection.py
reswarm/__init__.py
reswarm/reswarm.py
reswarm-0.0.19.dist-info/LICENSE
reswarm-0.0.19.dist-info/METADATA
reswarm-0.0.19.dist-info/WHEEL
reswarm-0.0.19.dist-info/top_level.txt
reswarm-0.0.19.dist-info/RECORD
