Metadata-Version: 2.1
Name: reswarm
Version: 0.0.19
Summary: Aids users in publishing data to a Record Evolution Datapod
Home-page: https://github.com/RecordEvolution/reswarm-python
Author: Record Evolution GmbH
Author-email: marko.petzold@record-evolution.de
License: MIT
Requires-Python: >=3.6
License-File: LICENSE
Requires-Dist: autobahn[asyncio,compression,serialization] ==22.3.2
